devdata/__init__.py
devdata/ai_utils.py
devdata/bigdata_utils.py
devdata/compression_utils.py
devdata/data_cleaning_utils.py
devdata/data_utils.py
devdata/data_viz_utils.py
devdata/encryption_utils.py
devdata/transform_utils.py
devdata-2.0.0.dist-info/licenses/LICENSE
devdata-2.0.0.dist-info/METADATA
devdata-2.0.0.dist-info/WHEEL
devdata-2.0.0.dist-info/top_level.txt
devdata-2.0.0.dist-info/RECORD
