Metadata-Version: 2.4
Name: devdata
Version: 2.0.0
Summary: A powerful set of utilities for data processing, visualization, and AI tasks.
Author-email: Aiden Wilson <visitoratbo@gmail.com>
License:                             Apache License
Requires-Python: >=3.7
License-File: LICENSE
Requires-Dist: asyncio
Requires-Dist: boto3
Requires-Dist: botocore
Requires-Dist: category_encoders
Requires-Dist: cryptography
Requires-Dist: dask
Requires-Dist: google
Requires-Dist: matplotlib
Requires-Dist: numpy
Requires-Dist: pandas
Requires-Dist: plotly
Requires-Dist: prefect
Requires-Dist: pyspark
Requires-Dist: scipy
Requires-Dist: seaborn
Requires-Dist: scikit-learn
Requires-Dist: tenacity
Requires-Dist: tensorflow
Requires-Dist: torch
Requires-Dist: torchvision
Requires-Dist: transformers
Dynamic: license-file
